listening_tool/__init__.py
listening_tool/config.py
listening_tool/listening_tool.py
listening_tool/logging_config.py
listening_tool/mic.py
listening_tool/recording_device.py
listening_tool/transcription.py
listening_tool-0.0.39.dist-info/LICENSE
listening_tool-0.0.39.dist-info/METADATA
listening_tool-0.0.39.dist-info/WHEEL
listening_tool-0.0.39.dist-info/RECORD
